{"cameraMode":{"drawMode":0,"name":"Shaded","section":"Shading Mode"},"sceneLighting":false,"audioPlay":false,"sceneViewState":{"m_AlwaysRefresh":false,"showFog":false,"showSkybox":false,"showFlares":true,"showImageEffects":true,"showParticleSystems":true,"showVisualEffectGraphs":true,"m_FxEnabled":true},"in2DMode":false,"pivot":{"x":-0.5398483276367188,"y":-0.1923236846923828,"z":-0.4459228515625},"rotation":{"x":0.01612892746925354,"y":-0.9722384214401245,"z":0.22284039855003358,"w":0.07039640843868256},"size":53.41621017456055,"orthographic":false}