{"cameraMode":{"drawMode":0,"name":"Shaded","section":"Shading Mode"},"sceneLighting":true,"audioPlay":false,"sceneViewState":{"m_AlwaysRefresh":false,"showFog":false,"showSkybox":true,"showFlares":true,"showImageEffects":true,"showParticleSystems":true,"showVisualEffectGraphs":true,"m_FxEnabled":true},"in2DMode":false,"pivot":{"x":-50.850345611572269,"y":190.7039031982422,"z":152.5058135986328},"rotation":{"x":-0.30520427227020266,"y":-0.6913074851036072,"z":0.502933919429779,"w":-0.419980525970459},"size":1.1660254001617432,"orthographic":false}